README.md
setup.py
AdminToolsDjango/CreateProject.py
AdminToolsDjango/__init__.py
AdminToolsDjango.egg-info/PKG-INFO
AdminToolsDjango.egg-info/SOURCES.txt
AdminToolsDjango.egg-info/dependency_links.txt
AdminToolsDjango.egg-info/top_level.txt
AdminToolsDjango/template-1.0/admin_script.py
AdminToolsDjango/template-1.0/manage.py
AdminToolsDjango/template-1.0/app_test/__init__.py
AdminToolsDjango/template-1.0/app_test/admin.py
AdminToolsDjango/template-1.0/app_test/apps.py
AdminToolsDjango/template-1.0/app_test/models.py
AdminToolsDjango/template-1.0/app_test/tests.py
AdminToolsDjango/template-1.0/app_test/urls.py
AdminToolsDjango/template-1.0/app_test/views.py
AdminToolsDjango/template-1.0/app_test/migrations/__init__.py
AdminToolsDjango/template-1.0/project_name/__init__.py
AdminToolsDjango/template-1.0/project_name/asgi.py
AdminToolsDjango/template-1.0/project_name/settings.py
AdminToolsDjango/template-1.0/project_name/urls.py
AdminToolsDjango/template-1.0/project_name/uwsgi.ini
AdminToolsDjango/template-1.0/project_name/wsgi.py
AdminToolsDjango/template-1.0/static/test.txt