Metadata-Version: 2.1
Name: AdminToolsDjango
Version: 1.0.6
Author: 孙亮
